kpireport_prometheus/__init__.py
kpireport_prometheus/alert_summary.py
kpireport_prometheus/datasource.py
kpireport_prometheus/templates/prometheus_alert_summary.html
kpireport_prometheus/templates/prometheus_alert_summary.md
kpireport_prometheus/templates/prometheus_alert_summary.slack
kpireport_prometheus-0.0.2.dist-info/METADATA
kpireport_prometheus-0.0.2.dist-info/WHEEL
kpireport_prometheus-0.0.2.dist-info/entry_points.txt
kpireport_prometheus-0.0.2.dist-info/top_level.txt
kpireport_prometheus-0.0.2.dist-info/RECORD
